{
  "annotations": {
    "list": [
      {
        "builtIn": 1,
        "datasource": "-- Grafana --",
        "enable": true,
        "hide": true,
        "iconColor": "rgba(0, 211, 255, 1)",
        "name": "Annotations & Alerts",
        "target": {
          "limit": 100,
          "matchAny": false,
          "tags": [],
          "type": "dashboard"
        },
        "type": "dashboard"
      }
    ]
  },
  "description": "",
  "editable": true,
  "fiscalYearStartMonth": 0,
  "gnetId": 5373,
  "graphTooltip": 0,
  "id": 2,
  "iteration": 1643551517025,
  "links": [],
  "liveNow": false,
  "panels": [
    {
      "collapsed": false,
      "gridPos": {
        "h": 1,
        "w": 24,
        "x": 0,
        "y": 0
      },
      "id": 41,
      "panels": [],
      "title": "System Stats",
      "type": "row"
    },
    {
      "fieldConfig": {
        "defaults": {
          "color": {
            "mode": "thresholds"
          },
          "mappings": [
            {
              "options": {
                "0": {
                  "text": "DOWN"
                },
                "1": {
                  "text": "UP"
                }
              },
              "type": "value"
            },
            {
              "options": {
                "match": "null",
                "result": {
                  "text": "DOWN"
                }
              },
              "type": "special"
            }
          ],
          "thresholds": {
            "mode": "absolute",
            "steps": [
              {
                "color": "#F2495C",
                "value": null
              },
              {
                "color": "#F2495C",
                "value": 0
              },
              {
                "color": "#299c46",
                "value": 1
              }
            ]
          },
          "unit": "none"
        },
        "overrides": []
      },
      "gridPos": {
        "h": 3,
        "w": 6,
        "x": 0,
        "y": 1
      },
      "id": 4,
      "links": [],
      "maxDataPoints": 100,
      "options": {
        "colorMode": "background",
        "graphMode": "none",
        "justifyMode": "auto",
        "orientation": "horizontal",
        "reduceOptions": {
          "calcs": [
            "lastNotNull"
          ],
          "fields": "",
          "values": false
        },
        "textMode": "auto"
      },
      "pluginVersion": "8.3.3",
      "targets": [
        {
          "datasource": {
            "type": "prometheus",
            "uid": "PBFA97CFB590B2093"
          },
          "exemplar": true,
          "expr": "up{instance=\"$instance\"}",
          "format": "time_series",
          "interval": "",
          "intervalFactor": 1,
          "legendFormat": "",
          "refId": "A"
        }
      ],
      "title": "Status",
      "transparent": true,
      "type": "stat"
    },
    {
      "fieldConfig": {
        "defaults": {
          "color": {
            "mode": "palette-classic"
          },
          "custom": {
            "axisLabel": "",
            "axisPlacement": "auto",
            "barAlignment": 0,
            "drawStyle": "line",
            "fillOpacity": 10,
            "gradientMode": "none",
            "hideFrom": {
              "legend": false,
              "tooltip": false,
              "viz": false
            },
            "lineInterpolation": "linear",
            "lineWidth": 1,
            "pointSize": 5,
            "scaleDistribution": {
              "type": "linear"
            },
            "showPoints": "never",
            "spanNulls": true,
            "stacking": {
              "group": "A",
              "mode": "none"
            },
            "thresholdsStyle": {
              "mode": "off"
            }
          },
          "mappings": [],
          "min": 0,
          "thresholds": {
            "mode": "absolute",
            "steps": [
              {
                "color": "green",
                "value": null
              },
              {
                "color": "red",
                "value": 80
              }
            ]
          },
          "unit": "bytes"
        },
        "overrides": []
      },
      "gridPos": {
        "h": 6,
        "w": 6,
        "x": 6,
        "y": 1
      },
      "id": 47,
      "links": [],
      "options": {
        "legend": {
          "calcs": [
            "lastNotNull",
            "max"
          ],
          "displayMode": "hidden",
          "placement": "bottom"
        },
        "tooltip": {
          "mode": "single"
        }
      },
      "pluginVersion": "8.3.3",
      "targets": [
        {
          "datasource": {
            "type": "prometheus",
            "uid": "PBFA97CFB590B2093"
          },
          "exemplar": true,
          "expr": "sum(jvm_memory_used_bytes{instance=\"$instance\", area=\"heap\"})",
          "format": "time_series",
          "interval": "",
          "intervalFactor": 2,
          "legendFormat": "used",
          "metric": "",
          "refId": "A",
          "step": 2400
        },
        {
          "datasource": {
            "type": "prometheus",
            "uid": "PBFA97CFB590B2093"
          },
          "exemplar": true,
          "expr": "sum(jvm_memory_committed_bytes{instance=\"$instance\", area=\"heap\"})",
          "format": "time_series",
          "interval": "",
          "intervalFactor": 2,
          "legendFormat": "committed",
          "refId": "B",
          "step": 2400
        },
        {
          "datasource": {
            "type": "prometheus",
            "uid": "PBFA97CFB590B2093"
          },
          "exemplar": true,
          "expr": "sum(jvm_memory_max_bytes{instance=\"$instance\", area=\"heap\"})",
          "format": "time_series",
          "interval": "",
          "intervalFactor": 2,
          "legendFormat": "max",
          "refId": "C",
          "step": 2400
        }
      ],
      "title": "JVM Heap",
      "transparent": true,
      "type": "timeseries"
    },
    {
      "fieldConfig": {
        "defaults": {
          "color": {
            "mode": "palette-classic"
          },
          "custom": {
            "axisLabel": "",
            "axisPlacement": "auto",
            "barAlignment": 0,
            "drawStyle": "line",
            "fillOpacity": 10,
            "gradientMode": "none",
            "hideFrom": {
              "legend": false,
              "tooltip": false,
              "viz": false
            },
            "lineInterpolation": "linear",
            "lineWidth": 1,
            "pointSize": 5,
            "scaleDistribution": {
              "type": "linear"
            },
            "showPoints": "never",
            "spanNulls": true,
            "stacking": {
              "group": "A",
              "mode": "none"
            },
            "thresholdsStyle": {
              "mode": "off"
            }
          },
          "decimals": 3,
          "mappings": [],
          "thresholds": {
            "mode": "absolute",
            "steps": [
              {
                "color": "green",
                "value": null
              },
              {
                "color": "red",
                "value": 80
              }
            ]
          },
          "unit": "percentunit"
        },
        "overrides": []
      },
      "gridPos": {
        "h": 6,
        "w": 6,
        "x": 12,
        "y": 1
      },
      "id": 32,
      "links": [],
      "options": {
        "legend": {
          "calcs": [
            "mean",
            "lastNotNull",
            "max",
            "min",
            "sum"
          ],
          "displayMode": "hidden",
          "placement": "right"
        },
        "tooltip": {
          "mode": "single"
        }
      },
      "pluginVersion": "8.3.3",
      "targets": [
        {
          "datasource": {
            "type": "prometheus",
            "uid": "PBFA97CFB590B2093"
          },
          "exemplar": true,
          "expr": "rate(process_cpu_usage{instance=\"$instance\"}[1m])*100",
          "format": "time_series",
          "hide": false,
          "instant": false,
          "interval": "",
          "intervalFactor": 1,
          "legendFormat": "CPU",
          "refId": "A"
        }
      ],
      "title": "Process CPU Usage",
      "transparent": true,
      "type": "timeseries"
    },
    {
      "aliasColors": {},
      "bars": false,
      "dashLength": 10,
      "dashes": false,
      "fill": 1,
      "fillGradient": 0,
      "gridPos": {
        "h": 6,
        "w": 6,
        "x": 18,
        "y": 1
      },
      "hiddenSeries": false,
      "id": 31,
      "legend": {
        "avg": false,
        "current": false,
        "max": false,
        "min": false,
        "show": false,
        "total": false,
        "values": false
      },
      "lines": true,
      "linewidth": 1,
      "links": [],
      "nullPointMode": "null",
      "options": {
        "alertThreshold": true
      },
      "percentage": false,
      "pluginVersion": "8.3.3",
      "pointradius": 2,
      "points": false,
      "renderer": "flot",
      "seriesOverrides": [],
      "spaceLength": 10,
      "stack": false,
      "steppedLine": false,
      "targets": [
        {
          "datasource": {
            "type": "prometheus",
            "uid": "PBFA97CFB590B2093"
          },
          "exemplar": true,
          "expr": "rate(system_cpu_usage{instance=\"$instance\"}[1m])*100",
          "format": "time_series",
          "interval": "",
          "intervalFactor": 1,
          "legendFormat": "",
          "refId": "A"
        }
      ],
      "thresholds": [],
      "timeRegions": [],
      "title": "CPU Usage",
      "tooltip": {
        "shared": true,
        "sort": 0,
        "value_type": "individual"
      },
      "transparent": true,
      "type": "graph",
      "xaxis": {
        "mode": "time",
        "show": true,
        "values": []
      },
      "yaxes": [
        {
          "format": "percent",
          "logBase": 1,
          "show": true
        },
        {
          "format": "short",
          "logBase": 1,
          "show": true
        }
      ],
      "yaxis": {
        "align": false
      }
    },
    {
      "fieldConfig": {
        "defaults": {
          "color": {
            "mode": "thresholds"
          },
          "decimals": 3,
          "mappings": [
            {
              "options": {
                "match": "null",
                "result": {
                  "text": "N/A"
                }
              },
              "type": "special"
            }
          ],
          "thresholds": {
            "mode": "absolute",
            "steps": [
              {
                "color": "#d44a3a",
                "value": null
              },
              {
                "color": "rgba(237, 129, 40, 0.89)",
                "value": 60
              },
              {
                "color": "#299c46",
                "value": 120
              }
            ]
          },
          "unit": "dthms"
        },
        "overrides": []
      },
      "gridPos": {
        "h": 3,
        "w": 6,
        "x": 0,
        "y": 4
      },
      "id": 18,
      "interval": "",
      "links": [],
      "maxDataPoints": 100,
      "options": {
        "colorMode": "value",
        "graphMode": "none",
        "justifyMode": "auto",
        "orientation": "horizontal",
        "reduceOptions": {
          "calcs": [
            "lastNotNull"
          ],
          "fields": "",
          "values": false
        },
        "textMode": "auto"
      },
      "pluginVersion": "8.3.3",
      "targets": [
        {
          "datasource": {
            "type": "prometheus",
            "uid": "PBFA97CFB590B2093"
          },
          "exemplar": true,
          "expr": "process_uptime_seconds{instance=\"$instance\"}",
          "format": "time_series",
          "interval": "",
          "intervalFactor": 1,
          "legendFormat": "",
          "refId": "A"
        }
      ],
      "title": "Up Time",
      "transparent": true,
      "type": "stat"
    },
    {
      "collapsed": true,
      "gridPos": {
        "h": 1,
        "w": 24,
        "x": 0,
        "y": 7
      },
      "id": 57,
      "panels": [
        {
          "fieldConfig": {
            "defaults": {
              "color": {
                "mode": "palette-classic"
              },
              "custom": {
                "axisLabel": "",
                "axisPlacement": "auto",
                "barAlignment": 0,
                "drawStyle": "line",
                "fillOpacity": 0,
                "gradientMode": "none",
                "hideFrom": {
                  "legend": false,
                  "tooltip": false,
                  "viz": false
                },
                "lineInterpolation": "stepAfter",
                "lineStyle": {
                  "fill": "solid"
                },
                "lineWidth": 1,
                "pointSize": 3,
                "scaleDistribution": {
                  "type": "linear"
                },
                "showPoints": "never",
                "spanNulls": true,
                "stacking": {
                  "group": "A",
                  "mode": "none"
                },
                "thresholdsStyle": {
                  "mode": "off"
                }
              },
              "mappings": [],
              "min": 0,
              "thresholds": {
                "mode": "absolute",
                "steps": [
                  {
                    "color": "green",
                    "value": null
                  },
                  {
                    "color": "red",
                    "value": 80
                  }
                ]
              },
              "unit": "short"
            },
            "overrides": []
          },
          "gridPos": {
            "h": 8,
            "w": 8,
            "x": 0,
            "y": 8
          },
          "id": 58,
          "interval": "1s",
          "links": [],
          "options": {
            "legend": {
              "calcs": [],
              "displayMode": "hidden",
              "placement": "right"
            },
            "tooltip": {
              "mode": "single"
            }
          },
          "pluginVersion": "8.3.3",
          "targets": [
            {
              "datasource": {
                "type": "prometheus",
                "uid": "PBFA97CFB590B2093"
              },
              "exemplar": true,
              "expr": "sum(ktor_http_server_requests_seconds_count{status=~\"^2..$\", route!=\"/metrics\"})",
              "format": "time_series",
              "interval": "",
              "intervalFactor": 1,
              "legendFormat": "2XX Success",
              "refId": "D",
              "step": 2
            }
          ],
          "title": "Success Count",
          "transparent": true,
          "type": "timeseries"
        },
        {
          "fieldConfig": {
            "defaults": {
              "color": {
                "mode": "continuous-reds"
              },
              "custom": {
                "axisLabel": "",
                "axisPlacement": "auto",
                "barAlignment": 0,
                "drawStyle": "line",
                "fillOpacity": 0,
                "gradientMode": "none",
                "hideFrom": {
                  "legend": false,
                  "tooltip": false,
                  "viz": false
                },
                "lineInterpolation": "stepAfter",
                "lineStyle": {
                  "fill": "solid"
                },
                "lineWidth": 1,
                "pointSize": 3,
                "scaleDistribution": {
                  "type": "linear"
                },
                "showPoints": "never",
                "spanNulls": true,
                "stacking": {
                  "group": "A",
                  "mode": "none"
                },
                "thresholdsStyle": {
                  "mode": "off"
                }
              },
              "mappings": [],
              "min": 0,
              "thresholds": {
                "mode": "absolute",
                "steps": [
                  {
                    "color": "green",
                    "value": null
                  },
                  {
                    "color": "red",
                    "value": 80
                  }
                ]
              },
              "unit": "short"
            },
            "overrides": []
          },
          "gridPos": {
            "h": 8,
            "w": 8,
            "x": 8,
            "y": 8
          },
          "id": 59,
          "interval": "1s",
          "links": [],
          "options": {
            "legend": {
              "calcs": [],
              "displayMode": "hidden",
              "placement": "right"
            },
            "tooltip": {
              "mode": "single"
            }
          },
          "pluginVersion": "8.3.3",
          "targets": [
            {
              "datasource": {
                "type": "prometheus",
                "uid": "PBFA97CFB590B2093"
              },
              "exemplar": true,
              "expr": "sum(ktor_http_server_requests_seconds_count{status=~\"^4..$\", route!=\"/metrics\"})",
              "format": "time_series",
              "interval": "",
              "intervalFactor": 1,
              "legendFormat": "4XX Errors",
              "refId": "C",
              "step": 2
            }
          ],
          "title": "API Error Count",
          "transparent": true,
          "type": "timeseries"
        },
        {
          "fieldConfig": {
            "defaults": {
              "color": {
                "mode": "continuous-purples"
              },
              "custom": {
                "axisLabel": "",
                "axisPlacement": "auto",
                "barAlignment": 0,
                "drawStyle": "line",
                "fillOpacity": 0,
                "gradientMode": "none",
                "hideFrom": {
                  "legend": false,
                  "tooltip": false,
                  "viz": false
                },
                "lineInterpolation": "stepAfter",
                "lineStyle": {
                  "fill": "solid"
                },
                "lineWidth": 1,
                "pointSize": 3,
                "scaleDistribution": {
                  "type": "linear"
                },
                "showPoints": "never",
                "spanNulls": true,
                "stacking": {
                  "group": "A",
                  "mode": "none"
                },
                "thresholdsStyle": {
                  "mode": "off"
                }
              },
              "mappings": [],
              "min": 0,
              "thresholds": {
                "mode": "absolute",
                "steps": [
                  {
                    "color": "green",
                    "value": null
                  },
                  {
                    "color": "red",
                    "value": 80
                  }
                ]
              },
              "unit": "short"
            },
            "overrides": []
          },
          "gridPos": {
            "h": 8,
            "w": 8,
            "x": 16,
            "y": 8
          },
          "id": 54,
          "interval": "1s",
          "links": [],
          "options": {
            "legend": {
              "calcs": [],
              "displayMode": "list",
              "placement": "right"
            },
            "tooltip": {
              "mode": "none"
            }
          },
          "pluginVersion": "8.3.3",
          "targets": [
            {
              "datasource": {
                "type": "prometheus",
                "uid": "PBFA97CFB590B2093"
              },
              "exemplar": true,
              "expr": "sum(ktor_http_server_requests_seconds_count{status=~\"^5..$\", route!=\"/metrics\"})",
              "format": "time_series",
              "interval": "",
              "intervalFactor": 1,
              "legendFormat": "5XX Errors",
              "refId": "B",
              "step": 4
            }
          ],
          "title": "Server Error Count",
          "transparent": true,
          "type": "timeseries"
        },
        {
          "fieldConfig": {
            "defaults": {
              "color": {
                "mode": "palette-classic"
              },
              "custom": {
                "axisLabel": "",
                "axisPlacement": "auto",
                "barAlignment": 0,
                "drawStyle": "line",
                "fillOpacity": 10,
                "gradientMode": "none",
                "hideFrom": {
                  "legend": false,
                  "tooltip": false,
                  "viz": false
                },
                "lineInterpolation": "stepAfter",
                "lineWidth": 1,
                "pointSize": 5,
                "scaleDistribution": {
                  "type": "linear"
                },
                "showPoints": "never",
                "spanNulls": true,
                "stacking": {
                  "group": "A",
                  "mode": "none"
                },
                "thresholdsStyle": {
                  "mode": "off"
                }
              },
              "mappings": [],
              "min": 0,
              "thresholds": {
                "mode": "absolute",
                "steps": [
                  {
                    "color": "green",
                    "value": null
                  },
                  {
                    "color": "red",
                    "value": 80
                  }
                ]
              },
              "unit": "short"
            },
            "overrides": []
          },
          "gridPos": {
            "h": 8,
            "w": 8,
            "x": 0,
            "y": 16
          },
          "id": 61,
          "interval": "1s",
          "links": [],
          "options": {
            "legend": {
              "calcs": [],
              "displayMode": "hidden",
              "placement": "right"
            },
            "tooltip": {
              "mode": "single"
            }
          },
          "pluginVersion": "8.3.3",
          "targets": [
            {
              "datasource": {
                "type": "prometheus",
                "uid": "PBFA97CFB590B2093"
              },
              "exemplar": true,
              "expr": "sum(ktor_http_server_requests_seconds_count{route!=\"/metrics\"})",
              "format": "time_series",
              "interval": "",
              "intervalFactor": 1,
              "legendFormat": "Total requests",
              "refId": "A",
              "step": 4
            }
          ],
          "title": "Total requests",
          "transparent": true,
          "type": "timeseries"
        },
        {
          "fieldConfig": {
            "defaults": {
              "color": {
                "mode": "palette-classic"
              },
              "custom": {
                "axisLabel": "",
                "axisPlacement": "auto",
                "barAlignment": 0,
                "drawStyle": "line",
                "fillOpacity": 10,
                "gradientMode": "none",
                "hideFrom": {
                  "legend": false,
                  "tooltip": false,
                  "viz": false
                },
                "lineInterpolation": "stepAfter",
                "lineWidth": 2,
                "pointSize": 5,
                "scaleDistribution": {
                  "type": "linear"
                },
                "showPoints": "never",
                "spanNulls": true,
                "stacking": {
                  "group": "A",
                  "mode": "none"
                },
                "thresholdsStyle": {
                  "mode": "off"
                }
              },
              "decimals": 6,
              "mappings": [],
              "min": 0,
              "thresholds": {
                "mode": "absolute",
                "steps": [
                  {
                    "color": "green",
                    "value": null
                  },
                  {
                    "color": "red",
                    "value": 80
                  }
                ]
              },
              "unit": "ms"
            },
            "overrides": []
          },
          "gridPos": {
            "h": 8,
            "w": 8,
            "x": 8,
            "y": 16
          },
          "id": 62,
          "links": [],
          "options": {
            "legend": {
              "calcs": [
                "lastNotNull"
              ],
              "displayMode": "hidden",
              "placement": "bottom"
            },
            "tooltip": {
              "mode": "single"
            }
          },
          "pluginVersion": "8.3.3",
          "targets": [
            {
              "datasource": {
                "type": "prometheus",
                "uid": "PBFA97CFB590B2093"
              },
              "exemplar": true,
              "expr": "avg(rate(ktor_http_server_requests_seconds{route!=\"/metrics\"}[1m]))",
              "format": "time_series",
              "instant": false,
              "interval": "",
              "intervalFactor": 1,
              "legendFormat": "Response time",
              "refId": "A"
            }
          ],
          "title": "Average Response time",
          "transparent": true,
          "type": "timeseries"
        },
        {
          "fieldConfig": {
            "defaults": {
              "color": {
                "mode": "palette-classic"
              },
              "custom": {
                "axisLabel": "",
                "axisPlacement": "auto",
                "barAlignment": 0,
                "drawStyle": "line",
                "fillOpacity": 10,
                "gradientMode": "none",
                "hideFrom": {
                  "legend": false,
                  "tooltip": false,
                  "viz": false
                },
                "lineInterpolation": "linear",
                "lineWidth": 1,
                "pointSize": 5,
                "scaleDistribution": {
                  "type": "linear"
                },
                "showPoints": "never",
                "spanNulls": true,
                "stacking": {
                  "group": "A",
                  "mode": "none"
                },
                "thresholdsStyle": {
                  "mode": "off"
                }
              },
              "mappings": [],
              "min": 0,
              "thresholds": {
                "mode": "absolute",
                "steps": [
                  {
                    "color": "green",
                    "value": null
                  },
                  {
                    "color": "red",
                    "value": 80
                  }
                ]
              },
              "unit": "short"
            },
            "overrides": []
          },
          "gridPos": {
            "h": 8,
            "w": 8,
            "x": 16,
            "y": 16
          },
          "id": 38,
          "interval": "1m",
          "links": [],
          "options": {
            "legend": {
              "calcs": [],
              "displayMode": "hidden",
              "placement": "bottom"
            },
            "tooltip": {
              "mode": "single"
            }
          },
          "pluginVersion": "8.3.3",
          "targets": [
            {
              "datasource": {
                "type": "prometheus",
                "uid": "PBFA97CFB590B2093"
              },
              "exemplar": true,
              "expr": "sum(rate(ktor_http_server_requests_seconds_count{route!=\"/metrics\"}[1m]))",
              "format": "time_series",
              "interval": "",
              "intervalFactor": 1,
              "legendFormat": "Total requests (min)",
              "refId": "D",
              "step": 2
            }
          ],
          "title": "Requests per minute",
          "transparent": true,
          "type": "timeseries"
        },
        {
          "fieldConfig": {
            "defaults": {
              "color": {
                "mode": "thresholds"
              },
              "custom": {
                "align": "auto",
                "displayMode": "auto"
              },
              "decimals": 3,
              "displayName": "",
              "mappings": [],
              "thresholds": {
                "mode": "absolute",
                "steps": [
                  {
                    "color": "green",
                    "value": null
                  },
                  {
                    "color": "red",
                    "value": 80
                  }
                ]
              },
              "unit": "short"
            },
            "overrides": []
          },
          "gridPos": {
            "h": 10,
            "w": 8,
            "x": 0,
            "y": 24
          },
          "id": 64,
          "interval": "",
          "links": [],
          "options": {
            "footer": {
              "fields": "",
              "reducer": [
                "sum"
              ],
              "show": false
            },
            "showHeader": true
          },
          "pluginVersion": "8.3.3",
          "targets": [
            {
              "datasource": {
                "type": "prometheus",
                "uid": "PBFA97CFB590B2093"
              },
              "exemplar": true,
              "expr": "topk(9, sort_desc(sum by(route, method) (ktor_http_server_requests_seconds_count{route!=\"/metrics\", status=~\"^2..$\"})))",
              "format": "time_series",
              "interval": "",
              "intervalFactor": 1,
              "legendFormat": "{{method}}  {{route}}",
              "refId": "A"
            }
          ],
          "title": "Top 10 APIs",
          "transformations": [
            {
              "id": "reduce",
              "options": {
                "includeTimeField": false,
                "reducers": [
                  "last"
                ]
              }
            }
          ],
          "transparent": true,
          "type": "table"
        },
        {
          "fieldConfig": {
            "defaults": {
              "color": {
                "mode": "thresholds"
              },
              "custom": {
                "align": "auto",
                "displayMode": "auto"
              },
              "decimals": 0,
              "displayName": "",
              "mappings": [],
              "thresholds": {
                "mode": "absolute",
                "steps": [
                  {
                    "color": "green",
                    "value": null
                  },
                  {
                    "color": "red",
                    "value": 80
                  }
                ]
              },
              "unit": "short"
            },
            "overrides": []
          },
          "gridPos": {
            "h": 10,
            "w": 8,
            "x": 8,
            "y": 24
          },
          "id": 65,
          "interval": "",
          "links": [],
          "options": {
            "footer": {
              "fields": "",
              "reducer": [
                "sum"
              ],
              "show": false
            },
            "showHeader": true
          },
          "pluginVersion": "8.3.3",
          "targets": [
            {
              "datasource": {
                "type": "prometheus",
                "uid": "PBFA97CFB590B2093"
              },
              "exemplar": false,
              "expr": "topk(10, sort_desc(sum by(route, method, status) (ktor_http_server_requests_seconds_count{route!=\"/metrics\", status=~\"^4..$\"})))",
              "format": "time_series",
              "hide": false,
              "instant": true,
              "interval": "",
              "intervalFactor": 1,
              "legendFormat": "{{method}} {{route}} {{status}}",
              "refId": "A"
            }
          ],
          "title": "Errors by API",
          "transformations": [
            {
              "id": "reduce",
              "options": {
                "includeTimeField": false,
                "reducers": [
                  "sum"
                ]
              }
            }
          ],
          "transparent": true,
          "type": "table"
        },
        {
          "fieldConfig": {
            "defaults": {
              "color": {
                "mode": "thresholds"
              },
              "custom": {
                "align": "auto",
                "displayMode": "auto"
              },
              "decimals": 0,
              "displayName": "",
              "mappings": [],
              "thresholds": {
                "mode": "absolute",
                "steps": [
                  {
                    "color": "green",
                    "value": null
                  },
                  {
                    "color": "red",
                    "value": 80
                  }
                ]
              },
              "unit": "short"
            },
            "overrides": []
          },
          "gridPos": {
            "h": 10,
            "w": 8,
            "x": 16,
            "y": 24
          },
          "id": 66,
          "interval": "",
          "links": [],
          "options": {
            "footer": {
              "fields": "",
              "reducer": [
                "sum"
              ],
              "show": false
            },
            "showHeader": true
          },
          "pluginVersion": "8.3.3",
          "targets": [
            {
              "datasource": {
                "type": "prometheus",
                "uid": "PBFA97CFB590B2093"
              },
              "exemplar": false,
              "expr": "topk(10, sort_desc(sum by(route, method, status) (ktor_http_server_requests_seconds_count{route!=\"/metrics\", status=~\"^5..$\"})))",
              "format": "time_series",
              "hide": false,
              "instant": true,
              "interval": "",
              "intervalFactor": 1,
              "legendFormat": "{{method}} {{route}} {{status}}",
              "refId": "A"
            }
          ],
          "title": "Errors by Server",
          "transformations": [
            {
              "id": "reduce",
              "options": {
                "includeTimeField": false,
                "reducers": [
                  "sum"
                ]
              }
            }
          ],
          "transparent": true,
          "type": "table"
        },
        {
          "fieldConfig": {
            "defaults": {
              "color": {
                "mode": "palette-classic"
              },
              "custom": {
                "axisLabel": "Time",
                "axisPlacement": "auto",
                "barAlignment": 0,
                "drawStyle": "line",
                "fillOpacity": 10,
                "gradientMode": "none",
                "hideFrom": {
                  "legend": false,
                  "tooltip": false,
                  "viz": false
                },
                "lineInterpolation": "linear",
                "lineWidth": 2,
                "pointSize": 5,
                "scaleDistribution": {
                  "type": "linear"
                },
                "showPoints": "never",
                "spanNulls": true,
                "stacking": {
                  "group": "A",
                  "mode": "none"
                },
                "thresholdsStyle": {
                  "mode": "off"
                }
              },
              "mappings": [],
              "min": 0,
              "thresholds": {
                "mode": "absolute",
                "steps": [
                  {
                    "color": "green",
                    "value": null
                  },
                  {
                    "color": "red",
                    "value": 80
                  }
                ]
              },
              "unit": "s"
            },
            "overrides": []
          },
          "gridPos": {
            "h": 9,
            "w": 8,
            "x": 0,
            "y": 34
          },
          "id": 67,
          "links": [],
          "options": {
            "legend": {
              "calcs": [
                "mean",
                "lastNotNull",
                "max",
                "min"
              ],
              "displayMode": "table",
              "placement": "bottom"
            },
            "tooltip": {
              "mode": "single"
            }
          },
          "pluginVersion": "8.3.3",
          "targets": [
            {
              "datasource": {
                "type": "prometheus",
                "uid": "PBFA97CFB590B2093"
              },
              "exemplar": true,
              "expr": "ktor_http_server_requests_seconds{route!=\"/metrics\", quantile=\"0.95\"}",
              "format": "time_series",
              "instant": false,
              "interval": "",
              "intervalFactor": 1,
              "legendFormat": "{{method}} {{route}} 95%",
              "refId": "A"
            }
          ],
          "title": "Response time of 95% of requests",
          "transparent": true,
          "type": "timeseries"
        },
        {
          "fieldConfig": {
            "defaults": {
              "color": {
                "mode": "palette-classic"
              },
              "custom": {
                "axisLabel": "Time",
                "axisPlacement": "auto",
                "barAlignment": 0,
                "drawStyle": "line",
                "fillOpacity": 10,
                "gradientMode": "none",
                "hideFrom": {
                  "legend": false,
                  "tooltip": false,
                  "viz": false
                },
                "lineInterpolation": "linear",
                "lineWidth": 2,
                "pointSize": 5,
                "scaleDistribution": {
                  "type": "linear"
                },
                "showPoints": "never",
                "spanNulls": true,
                "stacking": {
                  "group": "A",
                  "mode": "none"
                },
                "thresholdsStyle": {
                  "mode": "off"
                }
              },
              "mappings": [],
              "min": 0,
              "thresholds": {
                "mode": "absolute",
                "steps": [
                  {
                    "color": "green",
                    "value": null
                  },
                  {
                    "color": "red",
                    "value": 80
                  }
                ]
              },
              "unit": "s"
            },
            "overrides": []
          },
          "gridPos": {
            "h": 9,
            "w": 8,
            "x": 8,
            "y": 34
          },
          "id": 68,
          "links": [],
          "options": {
            "legend": {
              "calcs": [
                "mean",
                "lastNotNull",
                "max",
                "min"
              ],
              "displayMode": "table",
              "placement": "bottom"
            },
            "tooltip": {
              "mode": "single"
            }
          },
          "pluginVersion": "8.3.3",
          "targets": [
            {
              "datasource": {
                "type": "prometheus",
                "uid": "PBFA97CFB590B2093"
              },
              "exemplar": true,
              "expr": "ktor_http_server_requests_seconds{route!=\"/metrics\", quantile=\"0.9\"}",
              "format": "time_series",
              "instant": false,
              "interval": "",
              "intervalFactor": 1,
              "legendFormat": "{{method}} {{route}} 95%",
              "refId": "A"
            }
          ],
          "title": "Response time of 90% of requests",
          "transparent": true,
          "type": "timeseries"
        },
        {
          "fieldConfig": {
            "defaults": {
              "color": {
                "mode": "palette-classic"
              },
              "custom": {
                "axisLabel": "Time",
                "axisPlacement": "auto",
                "barAlignment": 0,
                "drawStyle": "line",
                "fillOpacity": 10,
                "gradientMode": "none",
                "hideFrom": {
                  "legend": false,
                  "tooltip": false,
                  "viz": false
                },
                "lineInterpolation": "linear",
                "lineWidth": 2,
                "pointSize": 5,
                "scaleDistribution": {
                  "type": "linear"
                },
                "showPoints": "never",
                "spanNulls": true,
                "stacking": {
                  "group": "A",
                  "mode": "none"
                },
                "thresholdsStyle": {
                  "mode": "off"
                }
              },
              "mappings": [],
              "min": 0,
              "thresholds": {
                "mode": "absolute",
                "steps": [
                  {
                    "color": "green",
                    "value": null
                  },
                  {
                    "color": "red",
                    "value": 80
                  }
                ]
              },
              "unit": "ms"
            },
            "overrides": []
          },
          "gridPos": {
            "h": 9,
            "w": 8,
            "x": 16,
            "y": 34
          },
          "id": 69,
          "links": [],
          "options": {
            "legend": {
              "calcs": [
                "mean",
                "lastNotNull",
                "max",
                "min"
              ],
              "displayMode": "table",
              "placement": "bottom"
            },
            "tooltip": {
              "mode": "single"
            }
          },
          "pluginVersion": "8.3.3",
          "targets": [
            {
              "datasource": {
                "type": "prometheus",
                "uid": "PBFA97CFB590B2093"
              },
              "exemplar": true,
              "expr": "ktor_http_server_requests_seconds{route!=\"/metrics\", quantile=\"0.5\"}",
              "format": "time_series",
              "interval": "",
              "intervalFactor": 1,
              "legendFormat": "{{method}} {{route}} 50%",
              "refId": "D"
            }
          ],
          "title": "Response time of 50% of requests",
          "transparent": true,
          "type": "timeseries"
        }
      ],
      "title": "Overall Requests",
      "type": "row"
    },
    {
      "collapsed": true,
      "gridPos": {
        "h": 1,
        "w": 24,
        "x": 0,
        "y": 8
      },
      "id": 37,
      "panels": [
        {
          "fieldConfig": {
            "defaults": {
              "color": {
                "mode": "palette-classic"
              },
              "custom": {
                "axisLabel": "",
                "axisPlacement": "auto",
                "barAlignment": 0,
                "drawStyle": "line",
                "fillOpacity": 0,
                "gradientMode": "none",
                "hideFrom": {
                  "legend": false,
                  "tooltip": false,
                  "viz": false
                },
                "lineInterpolation": "stepAfter",
                "lineStyle": {
                  "fill": "solid"
                },
                "lineWidth": 1,
                "pointSize": 3,
                "scaleDistribution": {
                  "type": "linear"
                },
                "showPoints": "never",
                "spanNulls": true,
                "stacking": {
                  "group": "A",
                  "mode": "none"
                },
                "thresholdsStyle": {
                  "mode": "off"
                }
              },
              "mappings": [],
              "min": 0,
              "thresholds": {
                "mode": "absolute",
                "steps": [
                  {
                    "color": "green",
                    "value": null
                  },
                  {
                    "color": "red",
                    "value": 80
                  }
                ]
              },
              "unit": "short"
            },
            "overrides": []
          },
          "gridPos": {
            "h": 8,
            "w": 8,
            "x": 0,
            "y": 9
          },
          "id": 34,
          "interval": "1s",
          "links": [],
          "options": {
            "legend": {
              "calcs": [],
              "displayMode": "hidden",
              "placement": "right"
            },
            "tooltip": {
              "mode": "single"
            }
          },
          "pluginVersion": "8.3.3",
          "targets": [
            {
              "datasource": {
                "type": "prometheus",
                "uid": "PBFA97CFB590B2093"
              },
              "exemplar": true,
              "expr": "sum(ktor_http_server_requests_seconds_count{status=~\"^2..$\", route!=\"/metrics\", instance=\"$instance\"})",
              "format": "time_series",
              "interval": "",
              "intervalFactor": 1,
              "legendFormat": "2XX Success",
              "refId": "D",
              "step": 2
            }
          ],
          "title": "Success Count",
          "transparent": true,
          "type": "timeseries"
        },
        {
          "fieldConfig": {
            "defaults": {
              "color": {
                "mode": "continuous-reds"
              },
              "custom": {
                "axisLabel": "",
                "axisPlacement": "auto",
                "barAlignment": 0,
                "drawStyle": "line",
                "fillOpacity": 0,
                "gradientMode": "none",
                "hideFrom": {
                  "legend": false,
                  "tooltip": false,
                  "viz": false
                },
                "lineInterpolation": "stepAfter",
                "lineStyle": {
                  "fill": "solid"
                },
                "lineWidth": 1,
                "pointSize": 3,
                "scaleDistribution": {
                  "type": "linear"
                },
                "showPoints": "never",
                "spanNulls": true,
                "stacking": {
                  "group": "A",
                  "mode": "none"
                },
                "thresholdsStyle": {
                  "mode": "off"
                }
              },
              "mappings": [],
              "min": 0,
              "thresholds": {
                "mode": "absolute",
                "steps": [
                  {
                    "color": "green",
                    "value": null
                  },
                  {
                    "color": "red",
                    "value": 80
                  }
                ]
              },
              "unit": "short"
            },
            "overrides": []
          },
          "gridPos": {
            "h": 8,
            "w": 8,
            "x": 8,
            "y": 9
          },
          "id": 55,
          "interval": "1s",
          "links": [],
          "options": {
            "legend": {
              "calcs": [],
              "displayMode": "hidden",
              "placement": "right"
            },
            "tooltip": {
              "mode": "single"
            }
          },
          "pluginVersion": "8.3.3",
          "targets": [
            {
              "datasource": {
                "type": "prometheus",
                "uid": "PBFA97CFB590B2093"
              },
              "exemplar": true,
              "expr": "sum(ktor_http_server_requests_seconds_count{status=~\"^4..$\", route!=\"/metrics\", instance=\"$instance\"})",
              "format": "time_series",
              "interval": "",
              "intervalFactor": 1,
              "legendFormat": "4XX Errors",
              "refId": "C",
              "step": 2
            }
          ],
          "title": "API Error Count",
          "transparent": true,
          "type": "timeseries"
        },
        {
          "fieldConfig": {
            "defaults": {
              "color": {
                "mode": "continuous-purples"
              },
              "custom": {
                "axisLabel": "",
                "axisPlacement": "auto",
                "barAlignment": 0,
                "drawStyle": "line",
                "fillOpacity": 0,
                "gradientMode": "none",
                "hideFrom": {
                  "legend": false,
                  "tooltip": false,
                  "viz": false
                },
                "lineInterpolation": "stepAfter",
                "lineStyle": {
                  "fill": "solid"
                },
                "lineWidth": 1,
                "pointSize": 3,
                "scaleDistribution": {
                  "type": "linear"
                },
                "showPoints": "never",
                "spanNulls": true,
                "stacking": {
                  "group": "A",
                  "mode": "none"
                },
                "thresholdsStyle": {
                  "mode": "off"
                }
              },
              "mappings": [],
              "min": 0,
              "thresholds": {
                "mode": "absolute",
                "steps": [
                  {
                    "color": "green",
                    "value": null
                  },
                  {
                    "color": "red",
                    "value": 80
                  }
                ]
              },
              "unit": "short"
            },
            "overrides": []
          },
          "gridPos": {
            "h": 8,
            "w": 8,
            "x": 16,
            "y": 9
          },
          "id": 60,
          "interval": "1s",
          "links": [],
          "options": {
            "legend": {
              "calcs": [],
              "displayMode": "list",
              "placement": "right"
            },
            "tooltip": {
              "mode": "none"
            }
          },
          "pluginVersion": "8.3.3",
          "targets": [
            {
              "datasource": {
                "type": "prometheus",
                "uid": "PBFA97CFB590B2093"
              },
              "exemplar": true,
              "expr": "sum(ktor_http_server_requests_seconds_count{status=~\"^5..$\", route!=\"/metrics\", instance=\"$instance\"})",
              "format": "time_series",
              "interval": "",
              "intervalFactor": 1,
              "legendFormat": "5XX Errors",
              "refId": "B",
              "step": 4
            }
          ],
          "title": "Server Error Count",
          "transparent": true,
          "type": "timeseries"
        },
        {
          "fieldConfig": {
            "defaults": {
              "color": {
                "mode": "palette-classic"
              },
              "custom": {
                "axisLabel": "",
                "axisPlacement": "auto",
                "barAlignment": 0,
                "drawStyle": "line",
                "fillOpacity": 10,
                "gradientMode": "none",
                "hideFrom": {
                  "legend": false,
                  "tooltip": false,
                  "viz": false
                },
                "lineInterpolation": "stepAfter",
                "lineWidth": 1,
                "pointSize": 5,
                "scaleDistribution": {
                  "type": "linear"
                },
                "showPoints": "never",
                "spanNulls": true,
                "stacking": {
                  "group": "A",
                  "mode": "none"
                },
                "thresholdsStyle": {
                  "mode": "off"
                }
              },
              "mappings": [],
              "min": 0,
              "thresholds": {
                "mode": "absolute",
                "steps": [
                  {
                    "color": "green",
                    "value": null
                  },
                  {
                    "color": "red",
                    "value": 80
                  }
                ]
              },
              "unit": "short"
            },
            "overrides": []
          },
          "gridPos": {
            "h": 8,
            "w": 8,
            "x": 0,
            "y": 17
          },
          "id": 50,
          "interval": "1s",
          "links": [],
          "options": {
            "legend": {
              "calcs": [],
              "displayMode": "hidden",
              "placement": "right"
            },
            "tooltip": {
              "mode": "single"
            }
          },
          "pluginVersion": "8.3.3",
          "targets": [
            {
              "datasource": {
                "type": "prometheus",
                "uid": "PBFA97CFB590B2093"
              },
              "exemplar": true,
              "expr": "sum(ktor_http_server_requests_seconds_count{route!=\"/metrics\", instance=\"$instance\"})",
              "format": "time_series",
              "interval": "",
              "intervalFactor": 1,
              "legendFormat": "Total requests",
              "refId": "A",
              "step": 4
            }
          ],
          "title": "Total requests",
          "transparent": true,
          "type": "timeseries"
        },
        {
          "fieldConfig": {
            "defaults": {
              "color": {
                "mode": "palette-classic"
              },
              "custom": {
                "axisLabel": "",
                "axisPlacement": "auto",
                "barAlignment": 0,
                "drawStyle": "line",
                "fillOpacity": 10,
                "gradientMode": "none",
                "hideFrom": {
                  "legend": false,
                  "tooltip": false,
                  "viz": false
                },
                "lineInterpolation": "stepAfter",
                "lineWidth": 2,
                "pointSize": 5,
                "scaleDistribution": {
                  "type": "linear"
                },
                "showPoints": "never",
                "spanNulls": true,
                "stacking": {
                  "group": "A",
                  "mode": "none"
                },
                "thresholdsStyle": {
                  "mode": "off"
                }
              },
              "decimals": 6,
              "mappings": [],
              "min": 0,
              "thresholds": {
                "mode": "absolute",
                "steps": [
                  {
                    "color": "green",
                    "value": null
                  },
                  {
                    "color": "red",
                    "value": 80
                  }
                ]
              },
              "unit": "ms"
            },
            "overrides": []
          },
          "gridPos": {
            "h": 8,
            "w": 8,
            "x": 8,
            "y": 17
          },
          "id": 29,
          "links": [],
          "options": {
            "legend": {
              "calcs": [
                "lastNotNull"
              ],
              "displayMode": "hidden",
              "placement": "bottom"
            },
            "tooltip": {
              "mode": "single"
            }
          },
          "pluginVersion": "8.3.3",
          "targets": [
            {
              "datasource": {
                "type": "prometheus",
                "uid": "PBFA97CFB590B2093"
              },
              "exemplar": true,
              "expr": "avg(rate(ktor_http_server_requests_seconds{route!=\"/metrics\", instance=\"$instance\"}[1m]))",
              "format": "time_series",
              "instant": false,
              "interval": "",
              "intervalFactor": 1,
              "legendFormat": "Response time",
              "refId": "A"
            }
          ],
          "title": "Average Response time",
          "transparent": true,
          "type": "timeseries"
        },
        {
          "fieldConfig": {
            "defaults": {
              "color": {
                "mode": "palette-classic"
              },
              "custom": {
                "axisLabel": "",
                "axisPlacement": "auto",
                "barAlignment": 0,
                "drawStyle": "line",
                "fillOpacity": 10,
                "gradientMode": "none",
                "hideFrom": {
                  "legend": false,
                  "tooltip": false,
                  "viz": false
                },
                "lineInterpolation": "linear",
                "lineWidth": 1,
                "pointSize": 5,
                "scaleDistribution": {
                  "type": "linear"
                },
                "showPoints": "never",
                "spanNulls": true,
                "stacking": {
                  "group": "A",
                  "mode": "none"
                },
                "thresholdsStyle": {
                  "mode": "off"
                }
              },
              "mappings": [],
              "min": 0,
              "thresholds": {
                "mode": "absolute",
                "steps": [
                  {
                    "color": "green",
                    "value": null
                  },
                  {
                    "color": "red",
                    "value": 80
                  }
                ]
              },
              "unit": "short"
            },
            "overrides": []
          },
          "gridPos": {
            "h": 8,
            "w": 8,
            "x": 16,
            "y": 17
          },
          "id": 63,
          "interval": "1m",
          "links": [],
          "options": {
            "legend": {
              "calcs": [],
              "displayMode": "hidden",
              "placement": "bottom"
            },
            "tooltip": {
              "mode": "single"
            }
          },
          "pluginVersion": "8.3.3",
          "targets": [
            {
              "datasource": {
                "type": "prometheus",
                "uid": "PBFA97CFB590B2093"
              },
              "exemplar": true,
              "expr": "sum(rate(ktor_http_server_requests_seconds_count{route!=\"/metrics\", instance=\"$instance\"}[1m]))",
              "format": "time_series",
              "interval": "",
              "intervalFactor": 1,
              "legendFormat": "Total requests (min)",
              "refId": "D",
              "step": 2
            }
          ],
          "title": "Requests per minute",
          "transparent": true,
          "type": "timeseries"
        },
        {
          "fieldConfig": {
            "defaults": {
              "color": {
                "mode": "thresholds"
              },
              "custom": {
                "align": "auto",
                "displayMode": "auto"
              },
              "decimals": 3,
              "displayName": "",
              "mappings": [],
              "thresholds": {
                "mode": "absolute",
                "steps": [
                  {
                    "color": "green",
                    "value": null
                  },
                  {
                    "color": "red",
                    "value": 80
                  }
                ]
              },
              "unit": "short"
            },
            "overrides": []
          },
          "gridPos": {
            "h": 10,
            "w": 8,
            "x": 0,
            "y": 25
          },
          "id": 16,
          "interval": "",
          "links": [],
          "options": {
            "footer": {
              "fields": "",
              "reducer": [
                "sum"
              ],
              "show": false
            },
            "showHeader": true
          },
          "pluginVersion": "8.3.3",
          "targets": [
            {
              "datasource": {
                "type": "prometheus",
                "uid": "PBFA97CFB590B2093"
              },
              "exemplar": true,
              "expr": "topk(9, sort_desc(sum by(route, method) (ktor_http_server_requests_seconds_count{instance=\"$instance\", route!=\"/metrics\", status=~\"^2..$\"})))",
              "format": "time_series",
              "interval": "",
              "intervalFactor": 1,
              "legendFormat": "{{method}}  {{route}}",
              "refId": "A"
            }
          ],
          "title": "Top 10 APIs",
          "transformations": [
            {
              "id": "reduce",
              "options": {
                "includeTimeField": false,
                "reducers": [
                  "last"
                ]
              }
            }
          ],
          "transparent": true,
          "type": "table"
        },
        {
          "fieldConfig": {
            "defaults": {
              "color": {
                "mode": "thresholds"
              },
              "custom": {
                "align": "auto",
                "displayMode": "auto"
              },
              "decimals": 0,
              "displayName": "",
              "mappings": [],
              "thresholds": {
                "mode": "absolute",
                "steps": [
                  {
                    "color": "green",
                    "value": null
                  },
                  {
                    "color": "red",
                    "value": 80
                  }
                ]
              },
              "unit": "short"
            },
            "overrides": []
          },
          "gridPos": {
            "h": 10,
            "w": 8,
            "x": 8,
            "y": 25
          },
          "id": 49,
          "interval": "",
          "links": [],
          "options": {
            "footer": {
              "fields": "",
              "reducer": [
                "sum"
              ],
              "show": false
            },
            "showHeader": true
          },
          "pluginVersion": "8.3.3",
          "targets": [
            {
              "datasource": {
                "type": "prometheus",
                "uid": "PBFA97CFB590B2093"
              },
              "exemplar": false,
              "expr": "topk(10, sort_desc(sum by(route, method, status) (ktor_http_server_requests_seconds_count{instance=\"$instance\", route!=\"/metrics\", status=~\"^4..$\"})))",
              "format": "time_series",
              "hide": false,
              "instant": true,
              "interval": "",
              "intervalFactor": 1,
              "legendFormat": "{{method}} {{route}} {{status}}",
              "refId": "A"
            }
          ],
          "title": "Errors by API",
          "transformations": [
            {
              "id": "reduce",
              "options": {
                "includeTimeField": false,
                "reducers": [
                  "sum"
                ]
              }
            }
          ],
          "transparent": true,
          "type": "table"
        },
        {
          "fieldConfig": {
            "defaults": {
              "color": {
                "mode": "thresholds"
              },
              "custom": {
                "align": "auto",
                "displayMode": "auto"
              },
              "decimals": 0,
              "displayName": "",
              "mappings": [],
              "thresholds": {
                "mode": "absolute",
                "steps": [
                  {
                    "color": "green",
                    "value": null
                  },
                  {
                    "color": "red",
                    "value": 80
                  }
                ]
              },
              "unit": "short"
            },
            "overrides": []
          },
          "gridPos": {
            "h": 10,
            "w": 8,
            "x": 16,
            "y": 25
          },
          "id": 53,
          "interval": "",
          "links": [],
          "options": {
            "footer": {
              "fields": "",
              "reducer": [
                "sum"
              ],
              "show": false
            },
            "showHeader": true
          },
          "pluginVersion": "8.3.3",
          "targets": [
            {
              "datasource": {
                "type": "prometheus",
                "uid": "PBFA97CFB590B2093"
              },
              "exemplar": false,
              "expr": "topk(10, sort_desc(sum by(route, method, status) (ktor_http_server_requests_seconds_count{instance=\"$instance\", route!=\"/metrics\", status=~\"^5..$\"})))",
              "format": "time_series",
              "hide": false,
              "instant": true,
              "interval": "",
              "intervalFactor": 1,
              "legendFormat": "{{method}} {{route}} {{status}}",
              "refId": "A"
            }
          ],
          "title": "Errors by Server",
          "transformations": [
            {
              "id": "reduce",
              "options": {
                "includeTimeField": false,
                "reducers": [
                  "sum"
                ]
              }
            }
          ],
          "transparent": true,
          "type": "table"
        },
        {
          "fieldConfig": {
            "defaults": {
              "color": {
                "mode": "palette-classic"
              },
              "custom": {
                "axisLabel": "Time",
                "axisPlacement": "auto",
                "barAlignment": 0,
                "drawStyle": "line",
                "fillOpacity": 10,
                "gradientMode": "none",
                "hideFrom": {
                  "legend": false,
                  "tooltip": false,
                  "viz": false
                },
                "lineInterpolation": "linear",
                "lineWidth": 2,
                "pointSize": 5,
                "scaleDistribution": {
                  "type": "linear"
                },
                "showPoints": "never",
                "spanNulls": true,
                "stacking": {
                  "group": "A",
                  "mode": "none"
                },
                "thresholdsStyle": {
                  "mode": "off"
                }
              },
              "mappings": [],
              "min": 0,
              "thresholds": {
                "mode": "absolute",
                "steps": [
                  {
                    "color": "green",
                    "value": null
                  },
                  {
                    "color": "red",
                    "value": 80
                  }
                ]
              },
              "unit": "s"
            },
            "overrides": []
          },
          "gridPos": {
            "h": 9,
            "w": 8,
            "x": 0,
            "y": 35
          },
          "id": 14,
          "links": [],
          "options": {
            "legend": {
              "calcs": [
                "mean",
                "lastNotNull",
                "max",
                "min"
              ],
              "displayMode": "table",
              "placement": "bottom"
            },
            "tooltip": {
              "mode": "single"
            }
          },
          "pluginVersion": "8.3.3",
          "targets": [
            {
              "datasource": {
                "type": "prometheus",
                "uid": "PBFA97CFB590B2093"
              },
              "exemplar": true,
              "expr": "ktor_http_server_requests_seconds{instance=\"$instance\", route!=\"/metrics\", quantile=\"0.95\"}",
              "format": "time_series",
              "instant": false,
              "interval": "",
              "intervalFactor": 1,
              "legendFormat": "{{method}} {{route}} 95%",
              "refId": "A"
            }
          ],
          "title": "Response time of 95% of requests",
          "transparent": true,
          "type": "timeseries"
        },
        {
          "fieldConfig": {
            "defaults": {
              "color": {
                "mode": "palette-classic"
              },
              "custom": {
                "axisLabel": "Time",
                "axisPlacement": "auto",
                "barAlignment": 0,
                "drawStyle": "line",
                "fillOpacity": 10,
                "gradientMode": "none",
                "hideFrom": {
                  "legend": false,
                  "tooltip": false,
                  "viz": false
                },
                "lineInterpolation": "linear",
                "lineWidth": 2,
                "pointSize": 5,
                "scaleDistribution": {
                  "type": "linear"
                },
                "showPoints": "never",
                "spanNulls": true,
                "stacking": {
                  "group": "A",
                  "mode": "none"
                },
                "thresholdsStyle": {
                  "mode": "off"
                }
              },
              "mappings": [],
              "min": 0,
              "thresholds": {
                "mode": "absolute",
                "steps": [
                  {
                    "color": "green",
                    "value": null
                  },
                  {
                    "color": "red",
                    "value": 80
                  }
                ]
              },
              "unit": "s"
            },
            "overrides": []
          },
          "gridPos": {
            "h": 9,
            "w": 8,
            "x": 8,
            "y": 35
          },
          "id": 51,
          "links": [],
          "options": {
            "legend": {
              "calcs": [
                "mean",
                "lastNotNull",
                "max",
                "min"
              ],
              "displayMode": "table",
              "placement": "bottom"
            },
            "tooltip": {
              "mode": "single"
            }
          },
          "pluginVersion": "8.3.3",
          "targets": [
            {
              "datasource": {
                "type": "prometheus",
                "uid": "PBFA97CFB590B2093"
              },
              "exemplar": true,
              "expr": "ktor_http_server_requests_seconds{instance=\"$instance\", route!=\"/metrics\", quantile=\"0.9\"}",
              "format": "time_series",
              "instant": false,
              "interval": "",
              "intervalFactor": 1,
              "legendFormat": "{{method}} {{route}} 95%",
              "refId": "A"
            }
          ],
          "title": "Response time of 90% of requests",
          "transparent": true,
          "type": "timeseries"
        },
        {
          "fieldConfig": {
            "defaults": {
              "color": {
                "mode": "palette-classic"
              },
              "custom": {
                "axisLabel": "Time",
                "axisPlacement": "auto",
                "barAlignment": 0,
                "drawStyle": "line",
                "fillOpacity": 10,
                "gradientMode": "none",
                "hideFrom": {
                  "legend": false,
                  "tooltip": false,
                  "viz": false
                },
                "lineInterpolation": "linear",
                "lineWidth": 2,
                "pointSize": 5,
                "scaleDistribution": {
                  "type": "linear"
                },
                "showPoints": "never",
                "spanNulls": true,
                "stacking": {
                  "group": "A",
                  "mode": "none"
                },
                "thresholdsStyle": {
                  "mode": "off"
                }
              },
              "mappings": [],
              "min": 0,
              "thresholds": {
                "mode": "absolute",
                "steps": [
                  {
                    "color": "green",
                    "value": null
                  },
                  {
                    "color": "red",
                    "value": 80
                  }
                ]
              },
              "unit": "ms"
            },
            "overrides": []
          },
          "gridPos": {
            "h": 9,
            "w": 8,
            "x": 16,
            "y": 35
          },
          "id": 43,
          "links": [],
          "options": {
            "legend": {
              "calcs": [
                "mean",
                "lastNotNull",
                "max",
                "min"
              ],
              "displayMode": "table",
              "placement": "bottom"
            },
            "tooltip": {
              "mode": "single"
            }
          },
          "pluginVersion": "8.3.3",
          "targets": [
            {
              "datasource": {
                "type": "prometheus",
                "uid": "PBFA97CFB590B2093"
              },
              "exemplar": true,
              "expr": "ktor_http_server_requests_seconds{instance=\"$instance\", route!=\"/metrics\", quantile=\"0.5\"}",
              "format": "time_series",
              "interval": "",
              "intervalFactor": 1,
              "legendFormat": "{{method}} {{route}} 50%",
              "refId": "D"
            }
          ],
          "title": "Response time of 50% of requests",
          "transparent": true,
          "type": "timeseries"
        }
      ],
      "title": "Requests",
      "type": "row"
    }
  ],
  "refresh": "10s",
  "schemaVersion": 34,
  "style": "dark",
  "tags": [
    "Ktor",
    "REST"
  ],
  "templating": {
    "list": [
      {
        "current": {
          "selected": false,
          "text": "192.168.1.230:8070",
          "value": "192.168.1.230:8070"
        },
        "datasource": {
          "type": "prometheus",
          "uid": "PBFA97CFB590B2093"
        },
        "definition": "label_values(instance)",
        "hide": 0,
        "includeAll": false,
        "label": "instance",
        "multi": false,
        "name": "instance",
        "options": [],
        "query": {
          "query": "label_values(instance)",
          "refId": "StandardVariableQuery"
        },
        "refresh": 2,
        "regex": "",
        "skipUrlSync": false,
        "sort": 0,
        "tagValuesQuery": "",
        "tagsQuery": "",
        "type": "query",
        "useTags": false
      }
    ]
  },
  "time": {
    "from": "now-5m",
    "to": "now"
  },
  "timepicker": {
    "refresh_intervals": [
      "5s",
      "10s",
      "30s",
      "1m",
      "5m",
      "15m",
      "30m",
      "1h",
      "2h",
      "1d"
    ],
    "time_options": [
      "5m",
      "15m",
      "1h",
      "6h",
      "12h",
      "24h",
      "2d",
      "7d",
      "30d"
    ]
  },
  "timezone": "",
  "title": "Ktor Monitoring",
  "uid": "omBsPz1Wz",
  "version": 1,
  "weekStart": ""
}